{
  "UpdateHash": "69f07313af612c7500e701df4f47aec68750f82fecbccf6bb7c7134e6bac8f69",
  "created_at": "2026-02-27T12:49:00.515449Z",
  "items": [
    {
      "title": "Xcode 26.3 (17C529)",
      "platform": "Xcode",
      "version": "26.3",
      "build": "17C529",
      "released": "2026-02-26",
      "release_notes_url": "https://developer.apple.com/go/?id=xcode-26_3-sdk-rn",
      "downloads_url": "https://developer.apple.com/download/applications",
      "source_card_url": "https://developer.apple.com/news/releases/"
    },
    {
      "title": "Xcode 26.4 beta 2 (17E5170d)",
      "platform": "Xcode",
      "version": "26.4 beta 2",
      "build": "17E5170d",
      "released": "2026-02-23",
      "release_notes_url": "https://developer.apple.com/go/?id=xcode-26_4-sdk-rn",
      "downloads_url": "https://developer.apple.com/download/applications",
      "source_card_url": "https://developer.apple.com/news/releases/"
    },
    {
      "title": "iOS 26.4 beta 2 (23E5218e)",
      "platform": "iOS",
      "version": "26.4 beta 2",
      "build": "23E5218e",
      "released": "2026-02-23",
      "release_notes_url": "https://developer.apple.com/go/?id=ios-26_4-rn",
      "downloads_url": "https://developer.apple.com/download/os",
      "source_card_url": "https://developer.apple.com/news/releases/"
    },
    {
      "title": "iPadOS 26.4 beta 2 (23E5218e)",
      "platform": "iPadOS",
      "version": "26.4 beta 2",
      "build": "23E5218e",
      "released": "2026-02-23",
      "release_notes_url": "https://developer.apple.com/go/?id=ipados-26_4-rn",
      "downloads_url": "https://developer.apple.com/download/os",
      "source_card_url": "https://developer.apple.com/news/releases/"
    },
    {
      "title": "macOS 26.4 beta 2 (25E5218f)",
      "platform": "macOS",
      "version": "26.4 beta 2",
      "build": "25E5218f",
      "released": "2026-02-23",
      "release_notes_url": "https://developer.apple.com/go/?id=macos-26_4-rn",
      "downloads_url": "https://developer.apple.com/download/os",
      "source_card_url": "https://developer.apple.com/news/releases/"
    },
    {
      "title": "tvOS 26.4 beta 2 (23L5219e)",
      "platform": "tvOS",
      "version": "26.4 beta 2",
      "build": "23L5219e",
      "released": "2026-02-23",
      "release_notes_url": "https://developer.apple.com/go/?id=tvos-26_4-rn",
      "downloads_url": "https://developer.apple.com/download/os",
      "source_card_url": "https://developer.apple.com/news/releases/"
    },
    {
      "title": "visionOS 26.4 beta 2 (23O5220e)",
      "platform": "visionOS",
      "version": "26.4 beta 2",
      "build": "23O5220e",
      "released": "2026-02-23",
      "release_notes_url": "https://developer.apple.com/go/?id=visionos-26_4-rn",
      "downloads_url": "https://developer.apple.com/download/os",
      "source_card_url": "https://developer.apple.com/news/releases/"
    },
    {
      "title": "watchOS 26.4 beta 2 (23T5221e)",
      "platform": "watchOS",
      "version": "26.4 beta 2",
      "build": "23T5221e",
      "released": "2026-02-23",
      "release_notes_url": "https://developer.apple.com/go/?id=watchos-26_4-rn",
      "downloads_url": "https://developer.apple.com/download/os",
      "source_card_url": "https://developer.apple.com/news/releases/"
    },
    {
      "title": "Xcode 26.1.1 (17B100)",
      "platform": "Xcode",
      "version": "26.1.1",
      "build": "17B100",
      "released": "2025-11-11",
      "release_notes_url": "https://developer.apple.com/go/?id=xcode-26_1-sdk-rn",
      "downloads_url": "https://developer.apple.com/download/applications",
      "source_card_url": "https://developer.apple.com/news/releases/"
    }
  ]
}