{
  "timestamp": "2025-12-04T18:01:12.951Z",
  "periods": {
    "volume": {
      "start": "2025-11-04T00:00:00.000Z",
      "end": "2025-12-04T00:00:00.000Z",
      "days": 30
    },
    "trend": {
      "start": "2025-11-27T00:00:00.000Z",
      "end": "2025-12-04T00:00:00.000Z",
      "days": 7
    }
  },
  "volume": {
    "metrics": {
      "totalRequests": {
        "value": 127575920,
        "formatted": "127.58M"
      },
      "bandwidth": {
        "bytes": 4218816563426,
        "formatted": "3.84 TB"
      },
      "cachedRequests": {
        "value": 127466199,
        "formatted": "127.47M"
      },
      "cacheRatio": {
        "value": 99.9,
        "formatted": "99.9%"
      }
    },
    "calculated": {
      "dailyAverage": {
        "requests": 4252530,
        "formatted": {
          "requests": "4.25M"
        }
      }
    }
  },
  "trend": {
    "metrics": {
      "totalRequests": {
        "value": 27037992,
        "formatted": "27.04M"
      },
      "bandwidth": {
        "bytes": 919868477147,
        "formatted": "856.69 GB"
      },
      "cachedRequests": {
        "value": 27020452,
        "formatted": "27.02M"
      }
    },
    "daily": [
      {
        "date": "2025-11-29",
        "requests": 2752583,
        "bytes": 91450942651
      },
      {
        "date": "2025-12-03",
        "requests": 4558209,
        "bytes": 158052203595
      },
      {
        "date": "2025-11-30",
        "requests": 2718865,
        "bytes": 89190899814
      },
      {
        "date": "2025-11-27",
        "requests": 3944614,
        "bytes": 134177975209
      },
      {
        "date": "2025-12-01",
        "requests": 4582423,
        "bytes": 158261045445
      },
      {
        "date": "2025-12-02",
        "requests": 4744674,
        "bytes": 161489054522
      },
      {
        "date": "2025-11-28",
        "requests": 3736624,
        "bytes": 127246355911
      }
    ],
    "geographic": {
      "topCountries": []
    }
  },
  "source": "sofa-metrics-collector"
}
