{
  "version": "3.0",
  "generated": "2025-10-04T18:39:10Z",
  "data_repo": {
    "commit": "5bdcef68f2118ba6852403769a45935b5b55c24f",
    "commit_short": "5bdcef6",
    "branch": "main",
    "commit_date": "2025-10-04T12:47:11Z",
    "dirty": true
  },
  "pipeline": {
    "gather": {
      "last_run": "2025-10-04T18:38:43Z",
      "sources": {
        "beta": {
          "last_fetch": "2025-10-04T18:38:41Z",
          "current_hash": "7e36a5e4b5e73f921745aec6e4c5474df9aff5a321d1263cb35b9b9a9bc41cfe",
          "previous_hash": "85dfdfc29fa091e2a158f1c4e19e7aa0414729012bd447e621a9d861535f88c4",
          "changed": true
        },
        "gdmf": {
          "last_fetch": "2025-10-04T18:38:39Z",
          "current_hash": "c01c95e8751bc14c5bc8e022fe2ddf2c8cc0fca512dd9cac359a7c6e749e882f",
          "previous_hash": "7eab43041b449f31899f9943a60756863e9481b5a7810027cc503af3c45324d3",
          "changed": true
        },
        "ipsw": {
          "last_fetch": "2025-10-04T18:38:41Z",
          "current_hash": "eeb211cb55b42a9c54308ef2b515b4a9d80bcf3ea041b4d8b81ea24ef6309c24",
          "previous_hash": "129c07c0ced25443aafd7d9238f60e90239bacc18b61e6940fd4a13d3e9ae107",
          "changed": true
        },
        "kev": {
          "last_fetch": "2025-10-04T18:38:39Z",
          "current_hash": "cf60558d5a83b4360c9d9afdaf3186de12a2a0ca420122d00cded13e8da71422",
          "previous_hash": "171b0692a5bf03a8d6d610d031a06b965fe11dc4a88d52e1f0df30ad8608ba11",
          "changed": true
        },
        "uma": {
          "last_fetch": "2025-10-04T18:38:43Z",
          "current_hash": "3c6a33fffaf11abef871ba6e7af543b89549929950bb03f9a19f3fe082f9bfbb",
          "previous_hash": "3c6a33fffaf11abef871ba6e7af543b89549929950bb03f9a19f3fe082f9bfbb",
          "changed": false
        },
        "xprotect": {
          "last_fetch": "2025-10-04T18:38:43Z",
          "current_hash": "2b1bab4ae28937f63e0fe6ac8d5db08ae057fa9bfe9f9be67fc02626c517938e",
          "previous_hash": "2b1bab4ae28937f63e0fe6ac8d5db08ae057fa9bfe9f9be67fc02626c517938e",
          "changed": false
        }
      },
      "changes_detected": [
        "beta",
        "gdmf",
        "ipsw",
        "kev"
      ]
    },
    "fetch": {
      "last_run_start": "2025-10-04T18:38:44Z",
      "last_run_end": "2025-10-04T18:39:09Z",
      "mode": "online",
      "releases_fetched": 608,
      "current_hash": "65c5d1c9f7482c3abdafcb8e2f53ccf2d865ccd44c982539d6df65c8e327979a",
      "previous_hash": "1f9d8ef4ecba27931a43e5d9a30f2b30339769ea0725cc9752d91427f3e9d78c",
      "performance_stats": "23.67 releases/sec"
    },
    "build": {
      "last_run": "2025-10-04T18:39:10Z",
      "v1": {
        "last_run": "2025-10-04T18:39:10Z",
        "platforms": {
          "ios": {
            "current_hash": "a7afa9eb34f0866a96250a6bf5794e96d36d146df38ac28657d9af2035f1b227",
            "previous_hash": null,
            "entries": 3,
            "size_bytes": 412060,
            "last_updated": "2025-10-04T18:39:10Z"
          },
          "macos": {
            "current_hash": "b69895cbf3b6894626a3b1a71585a5e6ce9ac81ffe30c6165e166aa20b9522f3",
            "previous_hash": null,
            "entries": 5,
            "size_bytes": 412060,
            "last_updated": "2025-10-04T18:39:10Z"
          },
          "safari": {
            "current_hash": "7cce4ac15fd3dbcfc6750e4544ea131f67179c6d536a434a1e0c211c43d35a77",
            "previous_hash": null,
            "entries": 3,
            "size_bytes": 412060,
            "last_updated": "2025-10-04T18:39:10Z"
          },
          "tvos": {
            "current_hash": "ce4b0ad2376e7c25177e288d0a4a98b9291c4b4ed135a848e1ceceb8c20a680d",
            "previous_hash": null,
            "entries": 2,
            "size_bytes": 412060,
            "last_updated": "2025-10-04T18:39:10Z"
          },
          "visionos": {
            "current_hash": "f55ea29b181138a31e9f0e4b5f70fae22dca18b057e4e5b71e8a33aa7b396dbc",
            "previous_hash": null,
            "entries": 2,
            "size_bytes": 412060,
            "last_updated": "2025-10-04T18:39:10Z"
          },
          "watchos": {
            "current_hash": "dfdcea7228fa55500e48520056d4cb14ffea61ed80b414a986f45f98026a8e29",
            "previous_hash": null,
            "entries": 0,
            "size_bytes": 412060,
            "last_updated": "2025-10-04T18:39:10Z"
          }
        }
      },
      "v2": {
        "last_run": "2025-10-04T18:39:10Z",
        "platforms": {
          "ios": {
            "current_hash": "001d7360e2da39efed953071187adc9b83590e9d1c634b1ccedc447a0f7e521b",
            "previous_hash": null,
            "entries": 3,
            "size_bytes": 347778,
            "last_updated": "2025-10-04T18:39:10Z"
          },
          "macos": {
            "current_hash": "b72d7f127f50546460886bf532ae94235b3a6d4653e8c6e58e6e7db207d824bb",
            "previous_hash": null,
            "entries": 5,
            "size_bytes": 347778,
            "last_updated": "2025-10-04T18:39:10Z"
          },
          "safari": {
            "current_hash": "7cce4ac15fd3dbcfc6750e4544ea131f67179c6d536a434a1e0c211c43d35a77",
            "previous_hash": null,
            "entries": 3,
            "size_bytes": 347778,
            "last_updated": "2025-10-04T18:39:10Z"
          },
          "tvos": {
            "current_hash": "934f7d5290bc2d69102c1de7cf6231a5497925e1e725cb8c208c736b4b59e0a4",
            "previous_hash": null,
            "entries": 2,
            "size_bytes": 347778,
            "last_updated": "2025-10-04T18:39:10Z"
          },
          "visionos": {
            "current_hash": "53180928857331a5098fe4332e8b028703dd2aba55e74f6bf19424a1fab3d8fd",
            "previous_hash": null,
            "entries": 2,
            "size_bytes": 347778,
            "last_updated": "2025-10-04T18:39:10Z"
          },
          "watchos": {
            "current_hash": "be929c4c164ba50532ab638639f46d4834b779ab8cb8fa148b91c47852a72f41",
            "previous_hash": null,
            "entries": 2,
            "size_bytes": 347778,
            "last_updated": "2025-10-04T18:39:10Z"
          }
        }
      }
    },
    "bulletin": {
      "last_run": "2025-10-04T18:39:10Z",
      "bulletin_count": 1,
      "cve_count": 8,
      "status": "completed",
      "current_hash": "ccb187854608226b433147283b39a83e472ae4bcc923b03ba4c31794df69de65",
      "previous_hash": "4f0390238d06a0c56926eb8a9e49b3cfe189424758fc499054045b7bc95dd4f2",
      "live_check_enabled": false
    },
    "enrich": null
  }
}