{
  "version": "3.0",
  "generated": "2026-07-13T01:03:57Z",
  "data_repo": {
    "commit": "c4b92960574fe339762acc305438e72c328cc571",
    "commit_short": "c4b9296",
    "branch": "main",
    "commit_date": "2026-07-12T19:08:40Z",
    "dirty": true
  },
  "pipeline": {
    "gather": {
      "last_run": "2026-07-13T01:03:34Z",
      "sources": {
        "beta": {
          "last_fetch": "2026-07-13T01:03:32Z",
          "current_hash": "0219dfe8b957e2a1469f1977acf187e8b592c1bf650f8df9f7e3b9afbaa8afd0",
          "previous_hash": "50c2fed09554a1e8d4fc3d8693f04c9059cec381044f6d479fc0173588d8009f",
          "changed": true
        },
        "gdmf": {
          "last_fetch": "2026-07-13T01:03:31Z",
          "current_hash": "1a32dead436c9a1f0ca6340a74f7f5f5013d660adc24a8678bc776bb6bc0ed3c",
          "previous_hash": "533b8b3ca385a8aa983f87de075bc8ae1307a2d5ac469bb83592e5b2a677c342",
          "changed": true
        },
        "ipsw": {
          "last_fetch": "2026-07-13T01:03:32Z",
          "current_hash": "2e9f9a1fa071dbb79f1b8aaddc159d3c463faabde1a60434705d1daebf6f12d5",
          "previous_hash": "aa7e2f854e1dbff1f8b0250d354a7e8c0d7fecae19bed594939d26a91853ddcb",
          "changed": true
        },
        "kev": {
          "last_fetch": "2026-07-13T01:03:31Z",
          "current_hash": "8d031766ba484aa7cced57af20a3891cb70da2d9e8735114a9d4067687515a80",
          "previous_hash": "e5ac0f888a8fe78d9553162a624d60c703d4595a8d7efebead2660fa2dccbbb1",
          "changed": true
        },
        "uma": {
          "last_fetch": "2026-07-13T01:03:33Z",
          "current_hash": "1c7b69fb4d64e26c57c8a97aa77b2db318eed2b07600aa7b8ae792ce77625d82",
          "previous_hash": "1c7b69fb4d64e26c57c8a97aa77b2db318eed2b07600aa7b8ae792ce77625d82",
          "changed": false
        },
        "xprotect": {
          "last_fetch": "2026-07-13T01:03:34Z",
          "current_hash": "ed5e4ebb85ccc99ea1c88d5848c71aadb3d51ac1cc9d8700d81c6eae38bdea75",
          "previous_hash": "ed5e4ebb85ccc99ea1c88d5848c71aadb3d51ac1cc9d8700d81c6eae38bdea75",
          "changed": false
        }
      },
      "changes_detected": [
        "beta",
        "gdmf",
        "ipsw",
        "kev"
      ]
    },
    "fetch": {
      "last_run_start": "2026-07-13T01:03:35Z",
      "last_run_end": "2026-07-13T01:03:57Z",
      "mode": "online",
      "releases_fetched": 695,
      "current_hash": "94c84261c2860d57f20789f3f9c007f512b7abc4fb147904a7668de705a7fae4",
      "previous_hash": "8bb463862b8c4777251d69110bbfdad42d82985eaf7f8bf505faec6739cd0e92",
      "performance_stats": "31.29 releases/sec"
    },
    "build": {
      "last_run": "2026-07-13T01:03:57Z",
      "v1": {
        "last_run": "2026-07-13T01:03:57Z",
        "platforms": {
          "ios": {
            "current_hash": "31f90ad8dfe4f5868bfed49669222c7df47d3ee770584bb421dbc45de75d9453",
            "previous_hash": null,
            "entries": 3,
            "size_bytes": 87193,
            "last_updated": "2026-07-13T01:03:57Z"
          },
          "macos": {
            "current_hash": "9ebecd402afb8da16912c7e7a1056fb47ac67dc179d87fe4c97c4c96214b4a23",
            "previous_hash": null,
            "entries": 5,
            "size_bytes": 468864,
            "last_updated": "2026-07-13T01:03:57Z"
          },
          "safari": {
            "current_hash": "b587084b84911acb7401efcba12c0700aec2cdf1bcb6adc44d751b928e4bbc2a",
            "previous_hash": null,
            "entries": 3,
            "size_bytes": 60531,
            "last_updated": "2026-07-13T01:03:57Z"
          },
          "tvos": {
            "current_hash": "830e25c550efc74161a5401c9fa07505d28e9f7c14ec45376d64489bccb5a209",
            "previous_hash": null,
            "entries": 2,
            "size_bytes": 32879,
            "last_updated": "2026-07-13T01:03:57Z"
          },
          "visionos": {
            "current_hash": "52e94ab4e5ac7bdb7ea30f3dd4c32d7ddd59e3899dcc4c5673c5da145b0ab6c5",
            "previous_hash": null,
            "entries": 2,
            "size_bytes": 38964,
            "last_updated": "2026-07-13T01:03:57Z"
          },
          "watchos": {
            "current_hash": "dfdcea7228fa55500e48520056d4cb14ffea61ed80b414a986f45f98026a8e29",
            "previous_hash": null,
            "entries": 0,
            "size_bytes": 126,
            "last_updated": "2026-07-13T01:03:57Z"
          }
        }
      },
      "v2": {
        "last_run": "2026-07-13T01:03:57Z",
        "platforms": {
          "ios": {
            "current_hash": "06ef0d81499b36835f30cd6cbbe14d2de06b2a24607036d318201f5b66ea1460",
            "previous_hash": null,
            "entries": 3,
            "size_bytes": 190599,
            "last_updated": "2026-07-13T01:03:57Z"
          },
          "macos": {
            "current_hash": "546c3dfffaad4fbba15d22fefe1ce772aed831b644f866118729c4ea9bf049f8",
            "previous_hash": null,
            "entries": 5,
            "size_bytes": 446513,
            "last_updated": "2026-07-13T01:03:57Z"
          },
          "safari": {
            "current_hash": "b587084b84911acb7401efcba12c0700aec2cdf1bcb6adc44d751b928e4bbc2a",
            "previous_hash": null,
            "entries": 3,
            "size_bytes": 60531,
            "last_updated": "2026-07-13T01:03:57Z"
          },
          "tvos": {
            "current_hash": "8dccb15c3ef0589ca87fa58d2d1a7dcee5bfd91a2f15971c4ad26ef607fab6ee",
            "previous_hash": null,
            "entries": 2,
            "size_bytes": 42084,
            "last_updated": "2026-07-13T01:03:57Z"
          },
          "visionos": {
            "current_hash": "649ad5482c1999cee7d45d5afb8fe71deaa17d23d136d0d6e6566063b3022291",
            "previous_hash": null,
            "entries": 2,
            "size_bytes": 49297,
            "last_updated": "2026-07-13T01:03:57Z"
          },
          "watchos": {
            "current_hash": "4978261b1284af1b6d143c9cda7d6ec15dd95305574e4bbb4ebdd1d3e9c628f0",
            "previous_hash": null,
            "entries": 2,
            "size_bytes": 52366,
            "last_updated": "2026-07-13T01:03:57Z"
          }
        }
      }
    },
    "bulletin": {
      "last_run": "2026-07-13T01:03:57Z",
      "bulletin_count": 1,
      "cve_count": 94,
      "status": "completed",
      "current_hash": "62f202f1a444823f9968fda25f26bdb2f12f57b3e70f826759eff1e1d9844671",
      "previous_hash": "777029461fda0f387e92871041865e08f53bf0a7042bc618699ede6458bb3ae7",
      "live_check_enabled": false
    },
    "enrich": null
  }
}