{
  "version": "3.0",
  "generated": "2026-06-12T19:16:30Z",
  "data_repo": {
    "commit": "69a6470a686d2e010b08a278de02354673e2f69f",
    "commit_short": "69a6470",
    "branch": "main",
    "commit_date": "2026-06-12T18:56:00Z",
    "dirty": true
  },
  "pipeline": {
    "gather": {
      "last_run": "2026-06-12T19:16:01Z",
      "sources": {
        "beta": {
          "last_fetch": "2026-06-12T19:15:59Z",
          "current_hash": "bb1a56f3cd050f88a364407ca8da15ebe78ce7db60b197b32e802c691cdf926c",
          "previous_hash": "5c664037ea31f9ef234ee26c908a42d1d71c2e0fe1e21b6ed8119195857152bc",
          "changed": true
        },
        "gdmf": {
          "last_fetch": "2026-06-12T19:15:58Z",
          "current_hash": "69ebaae4311a2d1fc421688fa57fa3f619867d6e3a413b2ea42b30db9c9de043",
          "previous_hash": "146e4c7288ce3bdeaa7be0ae23b537bfad8243c0fca73f72fff5a726c95b3207",
          "changed": true
        },
        "ipsw": {
          "last_fetch": "2026-06-12T19:15:59Z",
          "current_hash": "665d83b56f0f92e3a2804aa6aa4c0f24c08d762fdfdb1514e915d8910c6d53f8",
          "previous_hash": "a2b247a5ee3c258117bc1115d1e95584bf75b63b5b45014a3d50fcc26c04ec2d",
          "changed": true
        },
        "kev": {
          "last_fetch": "2026-06-12T19:15:58Z",
          "current_hash": "90d641e66793d0d487db34922bcdf63fb1063efb7a530de84f8f38abb7c97549",
          "previous_hash": "a803d4e941e126a2612f2a595a8669392bfd243d1479efd6f7f143a7abb29c37",
          "changed": true
        },
        "uma": {
          "last_fetch": "2026-06-12T19:16:01Z",
          "current_hash": "3ce9c9ba86e4fd9bb632e1d7a433623428171587fd21fa3042f3149f56f39f6a",
          "previous_hash": "ba09d707d276e912b39c8d643b49d25b03d2d471e5dedf162fbeee5ea57b8be6",
          "changed": true
        },
        "xprotect": {
          "last_fetch": "2026-06-12T19:16:01Z",
          "current_hash": "ed5e4ebb85ccc99ea1c88d5848c71aadb3d51ac1cc9d8700d81c6eae38bdea75",
          "previous_hash": "ed5e4ebb85ccc99ea1c88d5848c71aadb3d51ac1cc9d8700d81c6eae38bdea75",
          "changed": false
        }
      },
      "changes_detected": [
        "beta",
        "gdmf",
        "ipsw",
        "kev",
        "uma"
      ]
    },
    "fetch": {
      "last_run_start": "2026-06-12T19:16:02Z",
      "last_run_end": "2026-06-12T19:16:29Z",
      "mode": "online",
      "releases_fetched": 691,
      "current_hash": "a0e4bff91d0a383a5bfadfecdd06693f012e8bb1a7a333f7fe2308f372d70f54",
      "previous_hash": "ef2e31139bcacaa3c4d48a4b9703e697946fddc48d96c182913fef9f5256f3cc",
      "performance_stats": "25.38 releases/sec"
    },
    "build": {
      "last_run": "2026-06-12T19:16:29Z",
      "v1": {
        "last_run": "2026-06-12T19:16:29Z",
        "platforms": {
          "ios": {
            "current_hash": "502d2d372eae58dbd2a45d321f10f68110a41747266ab331efe321d3a3f36298",
            "previous_hash": null,
            "entries": 3,
            "size_bytes": 84035,
            "last_updated": "2026-06-12T19:16:29Z"
          },
          "macos": {
            "current_hash": "b1bd37dc3f46ffab2e2acfd0f6b96bae4876132e90cd24bb924cbd343b00ad67",
            "previous_hash": null,
            "entries": 5,
            "size_bytes": 462517,
            "last_updated": "2026-06-12T19:16:29Z"
          },
          "safari": {
            "current_hash": "ddc76aca09789e4bc320e9eaf7ec9e28a8df27653078b93fe2822bb0d8026a89",
            "previous_hash": null,
            "entries": 3,
            "size_bytes": 49634,
            "last_updated": "2026-06-12T19:16:29Z"
          },
          "tvos": {
            "current_hash": "830e25c550efc74161a5401c9fa07505d28e9f7c14ec45376d64489bccb5a209",
            "previous_hash": null,
            "entries": 2,
            "size_bytes": 32879,
            "last_updated": "2026-06-12T19:16:29Z"
          },
          "visionos": {
            "current_hash": "52e94ab4e5ac7bdb7ea30f3dd4c32d7ddd59e3899dcc4c5673c5da145b0ab6c5",
            "previous_hash": null,
            "entries": 2,
            "size_bytes": 38964,
            "last_updated": "2026-06-12T19:16:29Z"
          },
          "watchos": {
            "current_hash": "dfdcea7228fa55500e48520056d4cb14ffea61ed80b414a986f45f98026a8e29",
            "previous_hash": null,
            "entries": 0,
            "size_bytes": 126,
            "last_updated": "2026-06-12T19:16:29Z"
          }
        }
      },
      "v2": {
        "last_run": "2026-06-12T19:16:29Z",
        "platforms": {
          "ios": {
            "current_hash": "cf39b33a03b58c642ae393baf74ce045162531406e72d10f7c3dcd7219e227b7",
            "previous_hash": null,
            "entries": 3,
            "size_bytes": 193293,
            "last_updated": "2026-06-12T19:16:29Z"
          },
          "macos": {
            "current_hash": "b62bd0301e7c4e56c22b817af347e393fc77d5ccd7041a7942c215840166b41e",
            "previous_hash": null,
            "entries": 5,
            "size_bytes": 444826,
            "last_updated": "2026-06-12T19:16:29Z"
          },
          "safari": {
            "current_hash": "ddc76aca09789e4bc320e9eaf7ec9e28a8df27653078b93fe2822bb0d8026a89",
            "previous_hash": null,
            "entries": 3,
            "size_bytes": 49634,
            "last_updated": "2026-06-12T19:16:29Z"
          },
          "tvos": {
            "current_hash": "a5ac58820f38020b16d7942eac0c6bff99ecfe5774f22445b12b2fdcff7e2bf6",
            "previous_hash": null,
            "entries": 2,
            "size_bytes": 42311,
            "last_updated": "2026-06-12T19:16:29Z"
          },
          "visionos": {
            "current_hash": "8820cda75e88869203de5b5b8a3fb956259600986a103eaa414bd41af324416d",
            "previous_hash": null,
            "entries": 2,
            "size_bytes": 49484,
            "last_updated": "2026-06-12T19:16:29Z"
          },
          "watchos": {
            "current_hash": "1648a38c89ae6837416cf660674598d0295913a57a2fb9e294e30085f9970c3a",
            "previous_hash": null,
            "entries": 2,
            "size_bytes": 53347,
            "last_updated": "2026-06-12T19:16:29Z"
          }
        }
      }
    },
    "bulletin": {
      "last_run": "2026-06-12T19:16:30Z",
      "bulletin_count": 1,
      "cve_count": 62,
      "status": "completed",
      "current_hash": "acd5010a70f4cfebc6c2fbfc65ab3f2e56f9b78cb2e84338a7a3061c4c384b2f",
      "previous_hash": "7ea0f010930941acbf733fd6e790a1be783effac200649145f00b8a2c669eb68",
      "live_check_enabled": false
    },
    "enrich": null
  }
}