{
  "version": "3.0",
  "generated": "2025-11-18T18:43:56Z",
  "data_repo": {
    "commit": "4d0390a21489e4cb6d6b93b2531255c66ec84042",
    "commit_short": "4d0390a",
    "branch": "main",
    "commit_date": "2025-11-18T18:24:58Z",
    "dirty": true
  },
  "pipeline": {
    "gather": {
      "last_run": "2025-11-18T18:43:38Z",
      "sources": {
        "beta": {
          "last_fetch": "2025-11-18T18:43:37Z",
          "current_hash": "4ca6620adb78733d8544d0c63806e1f639b56abd4d162a4c6631becbac473dcb",
          "previous_hash": "c2142fa02c897de31ed6960355e1a68aa44292345405f8cab99ab9c0d6669196",
          "changed": true
        },
        "gdmf": {
          "last_fetch": "2025-11-18T18:43:36Z",
          "current_hash": "112255aee90aa2cd2db62d6eeae0d58155d67bc30536613da6c72268e3e25a11",
          "previous_hash": "d5c7cc0640f18b37087065a00089a908f93d6610df1dd5f9933b6e2adc261b8f",
          "changed": true
        },
        "ipsw": {
          "last_fetch": "2025-11-18T18:43:37Z",
          "current_hash": "4bfbcdd08416cfd1b2f9a2db2f1b7035ea71e433ff7fadaba911ea9cbcd53dd2",
          "previous_hash": "2cd6301a24b38ed81498f8d3ac2493807482c48999caf0f6a44d681bd4e1549c",
          "changed": true
        },
        "kev": {
          "last_fetch": "2025-11-18T18:43:36Z",
          "current_hash": "e29780eea25edb405c00af34e3147ad0f78138d23d65fda03c897124f55e3132",
          "previous_hash": "33e5f72aa5f06d504ae6bbd2374895575fbde6e2b7a2f6a04a0c89a935390081",
          "changed": true
        },
        "uma": {
          "last_fetch": "2025-11-18T18:43:38Z",
          "current_hash": "ea6e7ccd2f9a8a3dba81b434c0d841b79eae7496ae3bff5388da6857ffbb0c4e",
          "previous_hash": "a8cad1fcc6c648d7cca4fa3d1ee5c48bb01c8ed2409e804ddab910c5fbf1701c",
          "changed": true
        },
        "xprotect": {
          "last_fetch": "2025-11-18T18:43:38Z",
          "current_hash": "adee22bc7daefbf4ab77a4c921172401b77887a9e88fe32c7c01551c9e106747",
          "previous_hash": "adee22bc7daefbf4ab77a4c921172401b77887a9e88fe32c7c01551c9e106747",
          "changed": false
        }
      },
      "changes_detected": [
        "beta",
        "gdmf",
        "ipsw",
        "kev",
        "uma"
      ]
    },
    "fetch": {
      "last_run_start": "2025-11-18T18:43:38Z",
      "last_run_end": "2025-11-18T18:43:55Z",
      "mode": "online",
      "releases_fetched": 619,
      "current_hash": "00fe48f32a320fd39dcae98a5537098575589c21f074ae44350b35ff5cd7e880",
      "previous_hash": "0f7b6fe503aebd757638ad4f4a7d0120c092836981f46059b48f28f911fd9c7d",
      "performance_stats": "36.37 releases/sec"
    },
    "build": {
      "last_run": "2025-11-18T18:43:56Z",
      "v1": {
        "last_run": "2025-11-18T18:43:56Z",
        "platforms": {
          "ios": {
            "current_hash": "90af72e7bcdec54547f7d69a57e4d95066a15582234643db4fb039c686d3d3d7",
            "previous_hash": null,
            "entries": 3,
            "size_bytes": 412060,
            "last_updated": "2025-11-18T18:43:56Z"
          },
          "macos": {
            "current_hash": "4254d469e5106b4e32fc6fc04c8c88e0ed6297a246c2912efc1f90bdf49ea286",
            "previous_hash": null,
            "entries": 5,
            "size_bytes": 412060,
            "last_updated": "2025-11-18T18:43:56Z"
          },
          "safari": {
            "current_hash": "ddd42c3b9e09cb887143235e7659e7383fc292f7173380362f8d06f5bd8687cc",
            "previous_hash": null,
            "entries": 3,
            "size_bytes": 412060,
            "last_updated": "2025-11-18T18:43:56Z"
          },
          "tvos": {
            "current_hash": "29ce0c0754694b7bf0145965817652f1aa337bc2db70d1b8c78bad3dca29a05f",
            "previous_hash": null,
            "entries": 2,
            "size_bytes": 412060,
            "last_updated": "2025-11-18T18:43:56Z"
          },
          "visionos": {
            "current_hash": "9c7da8e858b968278ee09cd346fbc18da0a5e8a77797ea7d6ae2692649836742",
            "previous_hash": null,
            "entries": 2,
            "size_bytes": 412060,
            "last_updated": "2025-11-18T18:43:56Z"
          },
          "watchos": {
            "current_hash": "dfdcea7228fa55500e48520056d4cb14ffea61ed80b414a986f45f98026a8e29",
            "previous_hash": null,
            "entries": 0,
            "size_bytes": 412060,
            "last_updated": "2025-11-18T18:43:56Z"
          }
        }
      },
      "v2": {
        "last_run": "2025-11-18T18:43:56Z",
        "platforms": {
          "ios": {
            "current_hash": "01fe70830f5061d793267983d02c17065006ee9074b5ea4e3098d74f4f498d4d",
            "previous_hash": null,
            "entries": 3,
            "size_bytes": 347778,
            "last_updated": "2025-11-18T18:43:56Z"
          },
          "macos": {
            "current_hash": "4752d6a089ca66f832e6142da2fc7cc7cdafea1a9262572bbb5b312d16453c3f",
            "previous_hash": null,
            "entries": 5,
            "size_bytes": 347778,
            "last_updated": "2025-11-18T18:43:56Z"
          },
          "safari": {
            "current_hash": "ddd42c3b9e09cb887143235e7659e7383fc292f7173380362f8d06f5bd8687cc",
            "previous_hash": null,
            "entries": 3,
            "size_bytes": 347778,
            "last_updated": "2025-11-18T18:43:56Z"
          },
          "tvos": {
            "current_hash": "5a5edc9b694a456d097b87d455c5db3b73d7a5e7f74b1f6f69a7396c5b68f04b",
            "previous_hash": null,
            "entries": 2,
            "size_bytes": 347778,
            "last_updated": "2025-11-18T18:43:56Z"
          },
          "visionos": {
            "current_hash": "ee118f38dc065ce0e8dcbac59bb6dea3045aa354c51e09d6a9d37f8dcfa4a1b9",
            "previous_hash": null,
            "entries": 2,
            "size_bytes": 347778,
            "last_updated": "2025-11-18T18:43:56Z"
          },
          "watchos": {
            "current_hash": "50b24b74f6d25a47895169cd69686630141108528388d55d18e80f4002d1d7de",
            "previous_hash": null,
            "entries": 2,
            "size_bytes": 347778,
            "last_updated": "2025-11-18T18:43:56Z"
          }
        }
      }
    },
    "bulletin": {
      "last_run": "2025-11-18T18:43:56Z",
      "bulletin_count": 1,
      "cve_count": 118,
      "status": "completed",
      "current_hash": "d717e8619d91c7887af946a6cde770287c1cec8ff6eb2bc949c6d1068f4b7bc2",
      "previous_hash": "453833874415126826d3b5b401b8fd09269dc4865dff8e91e81d5fe796c45c30",
      "live_check_enabled": false
    },
    "enrich": null
  }
}